serviceplan/__init__.py
serviceplan/main.py
serviceplan-0.1.14.dist-info/METADATA
serviceplan-0.1.14.dist-info/WHEEL
serviceplan-0.1.14.dist-info/entry_points.txt
serviceplan-0.1.14.dist-info/RECORD
