Metadata-Version: 2.1
Name: serviceplan
Version: 0.1.14
Summary: Add your description here
Author-email: donglin <dong.lin@neusoft.com>
Requires-Python: >=3.12
Requires-Dist: black>=24.2.0
Requires-Dist: dlmail>=0.1.1
Requires-Dist: myproxy-8680>=1.0.1
Requires-Dist: mysql-connector-python>=8.3.0
Requires-Dist: mysql-connector==2.2.9
Requires-Dist: pip>=24.0
Requires-Dist: requests>=2.31.0
